{"schema_version":"ak-historian.pr4b0-r1p4.normalized-fragment.v1","normalization_version":"ak-historian.pr4b0-r1p4.normalized-fragment.v1","cycle_id":"cycle-20260714T191501088780287Z","symbol":"BNBUSDT","source_schema_version":"ak-historian.source-candle.binance-futures-um-1m.v1","source_schema_fingerprint":"sha256:eb5cc448b9333dd76a51fea226833f054d200c2c22a0b8ff3a4ba21905f7c1be","records":[{"market":"futures-um","symbol":"BNBUSDT","interval":"1m","period":"daily","source_date":"2026-07-14","open_time_ms":1784056200000,"open":"580.760","high":"580.760","low":"580.600","close":"580.690","volume":"96.33","close_time_ms":1784056259999,"quote_asset_volume":"55936.17220","number_of_trades":277,"taker_buy_base_volume":"27.38","taker_buy_quote_volume":"15898.29220"},{"market":"futures-um","symbol":"BNBUSDT","interval":"1m","period":"daily","source_date":"2026-07-14","open_time_ms":1784056260000,"open":"580.690","high":"580.900","low":"580.680","close":"580.820","volume":"122.39","close_time_ms":1784056319999,"quote_asset_volume":"71086.39590","number_of_trades":404,"taker_buy_base_volume":"77.26","taker_buy_quote_volume":"44871.83420"},{"market":"futures-um","symbol":"BNBUSDT","interval":"1m","period":"daily","source_date":"2026-07-14","open_time_ms":1784056320000,"open":"580.830","high":"581.150","low":"580.820","close":"581.150","volume":"66.43","close_time_ms":1784056379999,"quote_asset_volume":"38596.03210","number_of_trades":349,"taker_buy_base_volume":"61.95","taker_buy_quote_volume":"35992.85970"},{"market":"futures-um","symbol":"BNBUSDT","interval":"1m","period":"daily","source_date":"2026-07-14","open_time_ms":1784056380000,"open":"581.150","high":"581.310","low":"581.140","close":"581.190","volume":"198.71","close_time_ms":1784056439999,"quote_asset_volume":"115498.87640","number_of_trades":379,"taker_buy_base_volume":"144.03","taker_buy_quote_volume":"83714.12160"},{"market":"futures-um","symbol":"BNBUSDT","interval":"1m","period":"daily","source_date":"2026-07-14","open_time_ms":1784056440000,"open":"581.190","high":"581.240","low":"581.190","close":"581.220","volume":"86.34","close_time_ms":1784056499999,"quote_asset_volume":"50181.42950","number_of_trades":231,"taker_buy_base_volume":"44.16","taker_buy_quote_volume":"25666.05140"}],"fragment_hash":"sha256:fe3702df5b3224b6216a4affc4922f881947948b97220998cee23f503e8ec370"}
